porm/__init__.py
porm/errors.py
porm/model.py
porm/utils.py
porm/validators.py
porm/databases/__init__.py
porm/databases/api/__init__.py
porm/databases/api/mysql.py
porm/databases/api/drivers/__init__.py
porm/orms/__init__.py
porm/orms/mysql.py
porm/parsers/__init__.py
porm/parsers/mysql.py
porm/types/__init__.py
porm/types/core.py
Porm-0.0.28a0.dist-info/LICENSE
Porm-0.0.28a0.dist-info/METADATA
Porm-0.0.28a0.dist-info/WHEEL
Porm-0.0.28a0.dist-info/top_level.txt
Porm-0.0.28a0.dist-info/RECORD
